LICENSE.txt
MANIFEST.in
README.org
pyproject.toml
setup.cfg
setup.py
docs/README.rst
nix_prefetch_github/VERSION
nix_prefetch_github/__init__.py
nix_prefetch_github/__main__.py
nix_prefetch_github/alerter.py
nix_prefetch_github/dependency_injector.py
nix_prefetch_github/functor.py
nix_prefetch_github/github.py
nix_prefetch_github/hash.py
nix_prefetch_github/hash_converter.py
nix_prefetch_github/interfaces.py
nix_prefetch_github/list_remote.py
nix_prefetch_github/list_remote_factory.py
nix_prefetch_github/logging.py
nix_prefetch_github/prefetch.py
nix_prefetch_github/process_environment.py
nix_prefetch_github/repository_detector.py
nix_prefetch_github/revision_index.py
nix_prefetch_github/revision_index_factory.py
nix_prefetch_github/templates.py
nix_prefetch_github/test_github.py
nix_prefetch_github/test_hash.py
nix_prefetch_github/test_hash_converter.py
nix_prefetch_github/test_list_remote.py
nix_prefetch_github/test_list_remote_factory.py
nix_prefetch_github/test_logging.py
nix_prefetch_github/test_prefetch.py
nix_prefetch_github/test_prefetch_options.py
nix_prefetch_github/test_presenter.py
nix_prefetch_github/test_repository_detector.py
nix_prefetch_github/test_revision_index.py
nix_prefetch_github/test_revision_index_factory.py
nix_prefetch_github/tests.py
nix_prefetch_github/version.py
nix_prefetch_github/views.py
nix_prefetch_github.egg-info/PKG-INFO
nix_prefetch_github.egg-info/SOURCES.txt
nix_prefetch_github.egg-info/dependency_links.txt
nix_prefetch_github.egg-info/entry_points.txt
nix_prefetch_github.egg-info/top_level.txt
nix_prefetch_github/cli/__init__.py
nix_prefetch_github/cli/fetch_directory.py
nix_prefetch_github/cli/fetch_github.py
nix_prefetch_github/cli/fetch_latest_release.py
nix_prefetch_github/command/__init__.py
nix_prefetch_github/command/command_availability_checker.py
nix_prefetch_github/command/command_runner.py
nix_prefetch_github/command/test_command_availability_checker.py
nix_prefetch_github/command/test_command_runner.py
nix_prefetch_github/controller/__init__.py
nix_prefetch_github/controller/arguments.py
nix_prefetch_github/controller/nix_prefetch_github_controller.py
nix_prefetch_github/controller/nix_prefetch_github_directory_controller.py
