Metadata-Version: 2.1
Name: nix-prefetch-github
Version: 7.0.0
Summary: Prefetch source code from github for nix build tool
Home-page: https://github.com/seppeljordan/nix-prefetch-github
Author: Sebastian Jordan
Author-email: sebastian.jordan.mail@googlemail.com
Requires-Python: >=3.9
License-File: LICENSE.txt
